{
  "last_run": "2026-06-27 20:22 (เวลาไทย)",
  "signals": {
    "SPRC.BK": {
      "signal": "STRONG BUY",
      "score": 95
    },
    "LH.BK": {
      "signal": "STRONG BUY",
      "score": 90
    },
    "PLANB.BK": {
      "signal": "STRONG BUY",
      "score": 90
    },
    "JMT.BK": {
      "signal": "STRONG BUY",
      "score": 85
    },
    "SJWD.BK": {
      "signal": "STRONG BUY",
      "score": 82
    },
    "TPIPL.BK": {
      "signal": "STRONG BUY",
      "score": 78
    },
    "CPN.BK": {
      "signal": "STRONG BUY",
      "score": 77
    },
    "HMPRO.BK": {
      "signal": "STRONG BUY",
      "score": 77
    },
    "TU.BK": {
      "signal": "STRONG BUY",
      "score": 77
    },
    "AEONTS.BK": {
      "signal": "STRONG BUY",
      "score": 77
    },
    "DOHOME.BK": {
      "signal": "STRONG BUY",
      "score": 77
    },
    "ERW.BK": {
      "signal": "STRONG BUY",
      "score": 77
    },
    "QH.BK": {
      "signal": "STRONG BUY",
      "score": 77
    },
    "TKN.BK": {
      "signal": "STRONG BUY",
      "score": 77
    },
    "TOA.BK": {
      "signal": "STRONG BUY",
      "score": 77
    },
    "TQM.BK": {
      "signal": "STRONG BUY",
      "score": 77
    },
    "BDMS.BK": {
      "signal": "STRONG BUY",
      "score": 76
    },
    "GLOBAL.BK": {
      "signal": "STRONG BUY",
      "score": 76
    },
    "MTC.BK": {
      "signal": "STRONG BUY",
      "score": 76
    },
    "TOP.BK": {
      "signal": "STRONG BUY",
      "score": 76
    },
    "CBG.BK": {
      "signal": "BUY",
      "score": 72
    },
    "BCH.BK": {
      "signal": "BUY",
      "score": 72
    },
    "THANI.BK": {
      "signal": "BUY",
      "score": 72
    },
    "BJC.BK": {
      "signal": "BUY",
      "score": 69
    },
    "SAWAD.BK": {
      "signal": "BUY",
      "score": 68
    },
    "AOT.BK": {
      "signal": "BUY",
      "score": 67
    },
    "DCC.BK": {
      "signal": "BUY",
      "score": 65
    },
    "SAPPE.BK": {
      "signal": "BUY",
      "score": 64
    },
    "SINGER.BK": {
      "signal": "BUY",
      "score": 64
    },
    "CPF.BK": {
      "signal": "BUY",
      "score": 63
    },
    "BEC.BK": {
      "signal": "BUY",
      "score": 63
    },
    "BLA.BK": {
      "signal": "BUY",
      "score": 63
    },
    "HENG.BK": {
      "signal": "BUY",
      "score": 63
    },
    "JMART.BK": {
      "signal": "BUY",
      "score": 63
    },
    "MAJOR.BK": {
      "signal": "BUY",
      "score": 63
    },
    "CK.BK": {
      "signal": "BUY",
      "score": 62
    },
    "CKP.BK": {
      "signal": "BUY",
      "score": 62
    },
    "PRM.BK": {
      "signal": "BUY",
      "score": 62
    },
    "BH.BK": {
      "signal": "WATCH",
      "score": 59
    },
    "CENTEL.BK": {
      "signal": "WATCH",
      "score": 59
    },
    "KBANK.BK": {
      "signal": "WATCH",
      "score": 59
    },
    "SCB.BK": {
      "signal": "WATCH",
      "score": 59
    },
    "TTB.BK": {
      "signal": "WATCH",
      "score": 59
    },
    "CHG.BK": {
      "signal": "WATCH",
      "score": 59
    },
    "MC.BK": {
      "signal": "WATCH",
      "score": 59
    },
    "ONEE.BK": {
      "signal": "WATCH",
      "score": 59
    },
    "GUNKUL.BK": {
      "signal": "WATCH",
      "score": 58
    },
    "BTS.BK": {
      "signal": "WATCH",
      "score": 56
    },
    "EGCO.BK": {
      "signal": "WATCH",
      "score": 56
    },
    "RATCH.BK": {
      "signal": "WATCH",
      "score": 56
    },
    "ACE.BK": {
      "signal": "WATCH",
      "score": 56
    },
    "BAM.BK": {
      "signal": "WATCH",
      "score": 56
    },
    "FORTH.BK": {
      "signal": "WATCH",
      "score": 56
    },
    "LANNA.BK": {
      "signal": "WATCH",
      "score": 56
    },
    "M.BK": {
      "signal": "WATCH",
      "score": 56
    },
    "MEGA.BK": {
      "signal": "WATCH",
      "score": 56
    },
    "ORI.BK": {
      "signal": "WATCH",
      "score": 56
    },
    "RBF.BK": {
      "signal": "WATCH",
      "score": 56
    },
    "SAK.BK": {
      "signal": "WATCH",
      "score": 56
    },
    "TLI.BK": {
      "signal": "WATCH",
      "score": 56
    },
    "VGI.BK": {
      "signal": "WATCH",
      "score": 56
    },
    "WHA.BK": {
      "signal": "WATCH",
      "score": 55
    },
    "DITTO.BK": {
      "signal": "WATCH",
      "score": 55
    },
    "GFPT.BK": {
      "signal": "WATCH",
      "score": 55
    },
    "SNNP.BK": {
      "signal": "WATCH",
      "score": 55
    },
    "AWC.BK": {
      "signal": "WATCH",
      "score": 52
    },
    "OSP.BK": {
      "signal": "WATCH",
      "score": 52
    },
    "TISCO.BK": {
      "signal": "WATCH",
      "score": 52
    },
    "BA.BK": {
      "signal": "WATCH",
      "score": 52
    },
    "DMT.BK": {
      "signal": "WATCH",
      "score": 52
    },
    "KKP.BK": {
      "signal": "WATCH",
      "score": 52
    },
    "GPSC.BK": {
      "signal": "WATCH",
      "score": 51
    },
    "KTB.BK": {
      "signal": "WATCH",
      "score": 51
    },
    "KTC.BK": {
      "signal": "WATCH",
      "score": 51
    },
    "MINT.BK": {
      "signal": "WATCH",
      "score": 51
    },
    "SCGP.BK": {
      "signal": "WATCH",
      "score": 51
    },
    "TIDLOR.BK": {
      "signal": "WATCH",
      "score": 51
    },
    "ICHI.BK": {
      "signal": "WATCH",
      "score": 51
    },
    "BBL.BK": {
      "signal": "WATCH",
      "score": 48
    },
    "KCE.BK": {
      "signal": "WATCH",
      "score": 48
    },
    "SCC.BK": {
      "signal": "WATCH",
      "score": 48
    },
    "AMATA.BK": {
      "signal": "WATCH",
      "score": 48
    },
    "AU.BK": {
      "signal": "WATCH",
      "score": 48
    },
    "BCP.BK": {
      "signal": "WATCH",
      "score": 48
    },
    "BCPG.BK": {
      "signal": "WATCH",
      "score": 48
    },
    "IRPC.BK": {
      "signal": "WATCH",
      "score": 46
    },
    "BEM.BK": {
      "signal": "AVOID",
      "score": 44
    },
    "BGRIM.BK": {
      "signal": "AVOID",
      "score": 44
    },
    "CRC.BK": {
      "signal": "AVOID",
      "score": 44
    },
    "WHAUP.BK": {
      "signal": "AVOID",
      "score": 44
    },
    "RS.BK": {
      "signal": "AVOID",
      "score": 40
    },
    "SISB.BK": {
      "signal": "AVOID",
      "score": 40
    },
    "BTG.BK": {
      "signal": "AVOID",
      "score": 39
    },
    "OR.BK": {
      "signal": "AVOID",
      "score": 34
    },
    "AP.BK": {
      "signal": "AVOID",
      "score": 32
    },
    "SIRI.BK": {
      "signal": "AVOID",
      "score": 32
    },
    "COM7.BK": {
      "signal": "AVOID",
      "score": 31
    },
    "AH.BK": {
      "signal": "AVOID",
      "score": 31
    },
    "PTT.BK": {
      "signal": "AVOID",
      "score": 28
    },
    "ILM.BK": {
      "signal": "AVOID",
      "score": 26
    },
    "PTG.BK": {
      "signal": "AVOID",
      "score": 26
    },
    "SPALI.BK": {
      "signal": "AVOID",
      "score": 26
    },
    "BRI.BK": {
      "signal": "AVOID",
      "score": 25
    },
    "TASCO.BK": {
      "signal": "AVOID",
      "score": 25
    },
    "NER.BK": {
      "signal": "AVOID",
      "score": 21
    },
    "SYNEX.BK": {
      "signal": "AVOID",
      "score": 21
    },
    "PTTGC.BK": {
      "signal": "AVOID",
      "score": 20
    },
    "BPP.BK": {
      "signal": "AVOID",
      "score": 20
    },
    "PSL.BK": {
      "signal": "AVOID",
      "score": 20
    },
    "STGT.BK": {
      "signal": "AVOID",
      "score": 20
    },
    "TTA.BK": {
      "signal": "AVOID",
      "score": 20
    },
    "ZEN.BK": {
      "signal": "AVOID",
      "score": 20
    },
    "CPALL.BK": {
      "signal": "AVOID",
      "score": 18
    },
    "AAV.BK": {
      "signal": "AVOID",
      "score": 18
    },
    "CHAYO.BK": {
      "signal": "AVOID",
      "score": 18
    },
    "HANA.BK": {
      "signal": "AVOID",
      "score": 18
    },
    "HUMAN.BK": {
      "signal": "AVOID",
      "score": 18
    },
    "ITC.BK": {
      "signal": "AVOID",
      "score": 18
    },
    "RCL.BK": {
      "signal": "AVOID",
      "score": 18
    },
    "BANPU.BK": {
      "signal": "AVOID",
      "score": 16
    },
    "IVL.BK": {
      "signal": "AVOID",
      "score": 16
    },
    "PTTEP.BK": {
      "signal": "AVOID",
      "score": 16
    },
    "TRUE.BK": {
      "signal": "AVOID",
      "score": 16
    },
    "GGC.BK": {
      "signal": "AVOID",
      "score": 16
    },
    "ADVANC.BK": {
      "signal": "AVOID",
      "score": 12
    },
    "DELTA.BK": {
      "signal": "AVOID",
      "score": 12
    },
    "EA.BK": {
      "signal": "AVOID",
      "score": 12
    },
    "GULF.BK": {
      "signal": "AVOID",
      "score": 12
    },
    "IIG.BK": {
      "signal": "AVOID",
      "score": 12
    },
    "JAS.BK": {
      "signal": "AVOID",
      "score": 12
    },
    "UV.BK": {
      "signal": "AVOID",
      "score": 12
    },
    "STA.BK": {
      "signal": "AVOID",
      "score": 8
    },
    "MU": {
      "signal": "STRONG BUY",
      "score": 90
    },
    "LRCX": {
      "signal": "STRONG BUY",
      "score": 90
    },
    "TER": {
      "signal": "STRONG BUY",
      "score": 90
    },
    "HD": {
      "signal": "STRONG BUY",
      "score": 90
    },
    "AFRM": {
      "signal": "STRONG BUY",
      "score": 82
    },
    "UPST": {
      "signal": "STRONG BUY",
      "score": 82
    },
    "TGT": {
      "signal": "STRONG BUY",
      "score": 82
    },
    "SBUX": {
      "signal": "STRONG BUY",
      "score": 77
    },
    "HON": {
      "signal": "STRONG BUY",
      "score": 77
    },
    "ETN": {
      "signal": "STRONG BUY",
      "score": 77
    },
    "TOST": {
      "signal": "STRONG BUY",
      "score": 76
    },
    "CRDO": {
      "signal": "BUY",
      "score": 74
    },
    "INTC": {
      "signal": "BUY",
      "score": 74
    },
    "KLAC": {
      "signal": "BUY",
      "score": 74
    },
    "AMAT": {
      "signal": "BUY",
      "score": 72
    },
    "ABBV": {
      "signal": "BUY",
      "score": 72
    },
    "CAT": {
      "signal": "BUY",
      "score": 72
    },
    "STX": {
      "signal": "BUY",
      "score": 70
    },
    "VRT": {
      "signal": "BUY",
      "score": 69
    },
    "WFC": {
      "signal": "BUY",
      "score": 69
    },
    "OKTA": {
      "signal": "BUY",
      "score": 68
    },
    "A": {
      "signal": "BUY",
      "score": 68
    },
    "TMO": {
      "signal": "BUY",
      "score": 68
    },
    "NVO": {
      "signal": "BUY",
      "score": 64
    },
    "MRK": {
      "signal": "BUY",
      "score": 64
    },
    "DE": {
      "signal": "BUY",
      "score": 64
    },
    "AMD": {
      "signal": "BUY",
      "score": 63
    },
    "SHOP": {
      "signal": "BUY",
      "score": 63
    },
    "TXN": {
      "signal": "BUY",
      "score": 63
    },
    "LOW": {
      "signal": "BUY",
      "score": 63
    },
    "CMG": {
      "signal": "BUY",
      "score": 63
    },
    "LLY": {
      "signal": "BUY",
      "score": 63
    },
    "HOOD": {
      "signal": "BUY",
      "score": 62
    },
    "WDC": {
      "signal": "BUY",
      "score": 62
    },
    "V": {
      "signal": "BUY",
      "score": 62
    },
    "PG": {
      "signal": "BUY",
      "score": 62
    },
    "ALAB": {
      "signal": "BUY",
      "score": 60
    },
    "JNJ": {
      "signal": "WATCH",
      "score": 59
    },
    "VRTX": {
      "signal": "WATCH",
      "score": 59
    },
    "URI": {
      "signal": "WATCH",
      "score": 58
    },
    "CRWD": {
      "signal": "WATCH",
      "score": 56
    },
    "KO": {
      "signal": "WATCH",
      "score": 56
    },
    "ELF": {
      "signal": "WATCH",
      "score": 55
    },
    "GE": {
      "signal": "WATCH",
      "score": 55
    },
    "RIOT": {
      "signal": "WATCH",
      "score": 55
    },
    "CVNA": {
      "signal": "WATCH",
      "score": 52
    },
    "TSM": {
      "signal": "WATCH",
      "score": 48
    },
    "ASML": {
      "signal": "WATCH",
      "score": 48
    },
    "SNOW": {
      "signal": "WATCH",
      "score": 48
    },
    "ANET": {
      "signal": "WATCH",
      "score": 48
    },
    "SOFI": {
      "signal": "WATCH",
      "score": 48
    },
    "MRVL": {
      "signal": "WATCH",
      "score": 48
    },
    "ADI": {
      "signal": "WATCH",
      "score": 48
    },
    "GS": {
      "signal": "WATCH",
      "score": 48
    },
    "MS": {
      "signal": "WATCH",
      "score": 48
    },
    "RTX": {
      "signal": "WATCH",
      "score": 48
    },
    "LNG": {
      "signal": "WATCH",
      "score": 47
    },
    "PANW": {
      "signal": "WATCH",
      "score": 45
    },
    "FTNT": {
      "signal": "WATCH",
      "score": 45
    },
    "UNH": {
      "signal": "WATCH",
      "score": 45
    },
    "JPM": {
      "signal": "AVOID",
      "score": 44
    },
    "AXP": {
      "signal": "AVOID",
      "score": 44
    },
    "REGN": {
      "signal": "AVOID",
      "score": 41
    },
    "PYPL": {
      "signal": "AVOID",
      "score": 40
    },
    "BAC": {
      "signal": "AVOID",
      "score": 39
    },
    "SMCI": {
      "signal": "AVOID",
      "score": 38
    },
    "QCOM": {
      "signal": "AVOID",
      "score": 34
    },
    "MELI": {
      "signal": "AVOID",
      "score": 32
    },
    "RBLX": {
      "signal": "AVOID",
      "score": 32
    },
    "DUOL": {
      "signal": "AVOID",
      "score": 32
    },
    "MA": {
      "signal": "AVOID",
      "score": 32
    },
    "BA": {
      "signal": "AVOID",
      "score": 32
    },
    "NET": {
      "signal": "AVOID",
      "score": 26
    },
    "DDOG": {
      "signal": "AVOID",
      "score": 26
    },
    "CLS": {
      "signal": "AVOID",
      "score": 26
    },
    "ONON": {
      "signal": "AVOID",
      "score": 26
    },
    "WMT": {
      "signal": "AVOID",
      "score": 26
    },
    "PEP": {
      "signal": "AVOID",
      "score": 26
    },
    "CELH": {
      "signal": "AVOID",
      "score": 26
    },
    "MSTR": {
      "signal": "AVOID",
      "score": 21
    },
    "AAPL": {
      "signal": "AVOID",
      "score": 21
    },
    "AVGO": {
      "signal": "AVOID",
      "score": 20
    },
    "ZS": {
      "signal": "AVOID",
      "score": 20
    },
    "HUBS": {
      "signal": "AVOID",
      "score": 20
    },
    "LULU": {
      "signal": "AVOID",
      "score": 20
    },
    "LMT": {
      "signal": "AVOID",
      "score": 20
    },
    "XOM": {
      "signal": "AVOID",
      "score": 20
    },
    "ARM": {
      "signal": "AVOID",
      "score": 18
    },
    "MARA": {
      "signal": "AVOID",
      "score": 18
    },
    "CLSK": {
      "signal": "AVOID",
      "score": 18
    },
    "PLTR": {
      "signal": "AVOID",
      "score": 16
    },
    "AMZN": {
      "signal": "AVOID",
      "score": 16
    },
    "MSFT": {
      "signal": "AVOID",
      "score": 16
    },
    "CRM": {
      "signal": "AVOID",
      "score": 16
    },
    "ADBE": {
      "signal": "AVOID",
      "score": 16
    },
    "INTU": {
      "signal": "AVOID",
      "score": 16
    },
    "BLK": {
      "signal": "AVOID",
      "score": 16
    },
    "MCD": {
      "signal": "AVOID",
      "score": 16
    },
    "CVX": {
      "signal": "AVOID",
      "score": 16
    },
    "SLB": {
      "signal": "AVOID",
      "score": 16
    },
    "OXY": {
      "signal": "AVOID",
      "score": 16
    },
    "BABA": {
      "signal": "AVOID",
      "score": 16
    },
    "JD": {
      "signal": "AVOID",
      "score": 16
    },
    "PDD": {
      "signal": "AVOID",
      "score": 16
    },
    "XPEV": {
      "signal": "AVOID",
      "score": 16
    },
    "NVDA": {
      "signal": "AVOID",
      "score": 12
    },
    "NOW": {
      "signal": "AVOID",
      "score": 12
    },
    "APP": {
      "signal": "AVOID",
      "score": 12
    },
    "TSLA": {
      "signal": "AVOID",
      "score": 12
    },
    "DKNG": {
      "signal": "AVOID",
      "score": 12
    },
    "GOOGL": {
      "signal": "AVOID",
      "score": 12
    },
    "GOOG": {
      "signal": "AVOID",
      "score": 12
    },
    "MDB": {
      "signal": "AVOID",
      "score": 12
    },
    "TEAM": {
      "signal": "AVOID",
      "score": 12
    },
    "PATH": {
      "signal": "AVOID",
      "score": 12
    },
    "IONQ": {
      "signal": "AVOID",
      "score": 12
    },
    "RGTI": {
      "signal": "AVOID",
      "score": 12
    },
    "QBTS": {
      "signal": "AVOID",
      "score": 12
    },
    "ASTS": {
      "signal": "AVOID",
      "score": 12
    },
    "OKLO": {
      "signal": "AVOID",
      "score": 12
    },
    "COST": {
      "signal": "AVOID",
      "score": 12
    },
    "NKE": {
      "signal": "AVOID",
      "score": 12
    },
    "ISRG": {
      "signal": "AVOID",
      "score": 12
    },
    "META": {
      "signal": "AVOID",
      "score": 8
    },
    "NFLX": {
      "signal": "AVOID",
      "score": 8
    },
    "COIN": {
      "signal": "AVOID",
      "score": 8
    },
    "ORCL": {
      "signal": "AVOID",
      "score": 8
    },
    "AI": {
      "signal": "AVOID",
      "score": 8
    },
    "RKLB": {
      "signal": "AVOID",
      "score": 8
    },
    "PFE": {
      "signal": "AVOID",
      "score": 8
    },
    "COP": {
      "signal": "AVOID",
      "score": 8
    },
    "BIDU": {
      "signal": "AVOID",
      "score": 8
    },
    "NIO": {
      "signal": "AVOID",
      "score": 8
    },
    "LI": {
      "signal": "AVOID",
      "score": 8
    }
  }
}